ywpi/__init__.py
ywpi/additional_types.py
ywpi/cli.py
ywpi/client.py
ywpi/connection.py
ywpi/decorators.py
ywpi/drive_adapters.py
ywpi/handle_args.py
ywpi/hub_models.py
ywpi/hub_pb2.py
ywpi/hub_pb2.pyi
ywpi/hub_pb2_grpc.py
ywpi/io_manager.py
ywpi/logger.py
ywpi/main.py
ywpi/method_schemes.py
ywpi/serialization.py
ywpi/settings.py
ywpi/stream.py
ywpi/tracking.py
ywpi/ytypes.py
ywpi/api/__init__.py
ywpi/api/aio.py
ywpi/api/base.py
ywpi/stub/generation.py
ywpi/stub/getattr.py
ywpi-0.1.2.dist-info/METADATA
ywpi-0.1.2.dist-info/WHEEL
ywpi-0.1.2.dist-info/entry_points.txt
ywpi-0.1.2.dist-info/top_level.txt
ywpi-0.1.2.dist-info/RECORD
