Metadata-Version: 2.4
Name: ywpi
Version: 0.1.2
Summary: Add your description here
Requires-Python: >=3.10
Requires-Dist: aiochannel>=1.3.0
Requires-Dist: grpcio-tools==1.64.0
Requires-Dist: pydantic>=2.11.7
Requires-Dist: watchfiles>=1.1.0
